{
  "db_name": "PostgreSQL",
  "query": "\n        SELECT id, role as \"role: Role\", username_id FROM roles where username_id=$1\n        ",
  "describe": {
    "columns": [
      {
        "ordinal": 0,
        "name": "id",
        "type_info": "Uuid"
      },
      {
        "ordinal": 1,
        "name": "role: Role",
        "type_info": {
          "Custom": {
            "name": "role_type",
            "kind": {
              "Enum": [
                "tutor",
                "admin",
                "helper"
              ]
            }
          }
        }
      },
      {
        "ordinal": 2,
        "name": "username_id",
        "type_info": "Uuid"
      }
    ],
    "parameters": {
      "Left": [
        "Uuid"
      ]
    },
    "nullable": [
      false,
      false,
      false
    ]
  },
  "hash": "4e8c8853c3febb5eac97b1770ca370a414f534041c706b52b61adb371887b9e9"
}
